ticktask/__init__.py
ticktask/core.py
ticktask/database.py
ticktask/task.py
ticktask/utils.py
ticktask-0.3.0.dist-info/licenses/LICENSE
ticktask-0.3.0.dist-info/METADATA
ticktask-0.3.0.dist-info/WHEEL
ticktask-0.3.0.dist-info/top_level.txt
ticktask-0.3.0.dist-info/RECORD
