Metadata-Version: 2.4
Name: ticktask
Version: 0.3.0
Summary: Lightweight Python library for scheduling functions at specified times.
Home-page: https://github.com/kkocinski/ticktask
Author: kkocinski
Author-email: kajetan.kocinski@gmail.com
License: MIT
Classifier: Programming Language :: Python :: 3
Classifier: License :: OSI Approved :: MIT License
Classifier: Operating System :: OS Independent
Classifier: Topic :: Software Development :: Libraries :: Python Modules
Requires-Python: >=3.12
License-File: LICENSE
Dynamic: license-file
